cremalink/__init__.py
cremalink/local_server.py
cremalink/clients/__init__.py
cremalink/clients/cloud.py
cremalink/core/__init__.py
cremalink/core/binary.py
cremalink/crypto/__init__.py
cremalink/devices/ECAM452.json
cremalink/devices/ECAM612.json
cremalink/devices/__init__.py
cremalink/domain/__init__.py
cremalink/domain/device.py
cremalink/domain/factory.py
cremalink/local_server_app/__init__.py
cremalink/local_server_app/api.py
cremalink/local_server_app/config.py
cremalink/local_server_app/device_adapter.py
cremalink/local_server_app/jobs.py
cremalink/local_server_app/logging.py
cremalink/local_server_app/models.py
cremalink/local_server_app/protocol.py
cremalink/local_server_app/state.py
cremalink/parsing/__init__.py
cremalink/parsing/monitor/__init__.py
cremalink/parsing/monitor/decode.py
cremalink/parsing/monitor/extractors.py
cremalink/parsing/monitor/frame.py
cremalink/parsing/monitor/model.py
cremalink/parsing/monitor/profile.py
cremalink/parsing/monitor/view.py
cremalink/parsing/properties/__init__.py
cremalink/parsing/properties/decode.py
cremalink/resources/__init__.py
cremalink/resources/api_config.json
cremalink/resources/api_config.py
cremalink/resources/lang.json
cremalink/transports/__init__.py
cremalink/transports/base.py
cremalink/transports/cloud/__init__.py
cremalink/transports/cloud/transport.py
cremalink/transports/local/__init__.py
cremalink/transports/local/transport.py
cremalink-0.1.0b15.dist-info/licenses/LICENSE
cremalink-0.1.0b15.dist-info/METADATA
cremalink-0.1.0b15.dist-info/WHEEL
cremalink-0.1.0b15.dist-info/entry_points.txt
cremalink-0.1.0b15.dist-info/top_level.txt
cremalink-0.1.0b15.dist-info/RECORD
