Metadata-Version: 2.4
Name: cremalink
Version: 0.1.0b15
Summary: Python library and local API server for monitoring and controlling IoT coffee machines.
Author-email: Midian Tekle Elfu <developer@midian.tekleelfu.de>
Maintainer-email: Midian Tekle Elfu <developer@midian.tekleelfu.de>
License-Expression: AGPL-3.0-or-later
Project-URL: homepage, https://github.com/miditkl/cremalink
Project-URL: source, https://github.com/miditkl/cremalink.git
Project-URL: issues, https://github.com/miditkl/cremalink/issues
Project-URL: download, https://github.com/miditkl/cremalink/archive/refs/heads/main.zip
Project-URL: funding, https://github.com/sponsors/miditkl
Keywords: Local Control,Cloud Control,Coffee Machine,IoT
Classifier: Development Status :: 4 - Beta
Classifier: Intended Audience :: Developers
Classifier: Intended Audience :: End Users/Desktop
Classifier: Intended Audience :: Information Technology
Classifier: Topic :: Software Development
Classifier: Topic :: Software Development :: Libraries :: Python Modules
Classifier: Topic :: System :: Monitoring
Classifier: Topic :: System :: Networking :: Monitoring
Classifier: Programming Language :: Python :: 3.13
Classifier: Programming Language :: Python :: 3.14
Classifier: Programming Language :: Python :: 3.15
Classifier: Operating System :: OS Independent
Requires-Python: >=3.13
License-File: LICENSE
Requires-Dist: requests>=2.32.0
Requires-Dist: pycryptodome>=3.20.0
Requires-Dist: fastapi>=0.128.0
Requires-Dist: uvicorn>=0.40.0
Requires-Dist: httpx>=0.28.0
Requires-Dist: pydantic>=2.12.0
Requires-Dist: pydantic-settings>=2.10.0
Provides-Extra: dev
Requires-Dist: cremalink[test]; extra == "dev"
Requires-Dist: cremalink[docs]; extra == "dev"
Requires-Dist: ipykernel==7.1.0; extra == "dev"
Requires-Dist: notebook==7.5.3; extra == "dev"
Provides-Extra: test
Requires-Dist: pytest==9.0.2; extra == "test"
Requires-Dist: pytest-asyncio==1.3.0; extra == "test"
Provides-Extra: docs
Requires-Dist: sphinx==9.1.0; extra == "docs"
Requires-Dist: sphinxcontrib-websupport==2.0.0; extra == "docs"
Requires-Dist: sphinx-rtd-theme==3.1.0; extra == "docs"
Dynamic: license-file
